oslex/__init__.py
oslex/py.typed
oslex-0.1.2.dist-info/METADATA
oslex-0.1.2.dist-info/WHEEL
oslex-0.1.2.dist-info/licenses/LICENSE
oslex-0.1.2.dist-info/RECORD
