Metadata-Version: 2.1
Name: oslex
Version: 0.1.2
Summary: OS-independent wrapper for shlex and mslex
Project-URL: Homepage, https://github.com/petamas/oslex
Project-URL: Bug Tracker, https://github.com/petamas/oslex/issues
Author-email: Tamás PEREGI <petamas@gmail.com>
License-File: LICENSE
Classifier: License :: OSI Approved :: MIT License
Classifier: Operating System :: MacOS
Classifier: Operating System :: Microsoft :: Windows
Classifier: Operating System :: POSIX
Classifier: Programming Language :: Python :: 3
Classifier: Programming Language :: Python :: 3.6
Classifier: Programming Language :: Python :: 3.7
Classifier: Programming Language :: Python :: 3.8
Classifier: Programming Language :: Python :: 3.9
Classifier: Programming Language :: Python :: 3.10
Classifier: Programming Language :: Python :: 3.11
Requires-Python: >=3.6
Requires-Dist: mslex
